{
  "schema_version": "v1",
  "updated_at": "2026-04-21T19:05:00+09:00",
  "items": [
    {
      "item_id": "auction-2024-97439-001",
      "case_no": "2024타경97439",
      "status": "candidate",
      "priority": 1,
      "region": "수원",
      "sub_region": "팔달구",
      "asset_type": "아파트",
      "minimum_price": 252700000,
      "market_price_avg": 347000000,
      "minimum_vs_avg_pct": -27.18,
      "rights_risk_level": "low",
      "occupancy_risk_level": "medium",
      "budget_fit": true,
      "recommendation": "review",
      "item_path": "auctions/items/2024타경97439.json"
    },
    {
      "item_id": "auction-2024-103242-001",
      "case_no": "2024타경103242",
      "status": "review",
      "priority": 2,
      "region": "수원",
      "sub_region": "장안구",
      "asset_type": "아파트",
      "minimum_price": 295400000,
      "market_price_avg": 423115900,
      "minimum_vs_avg_pct": -30.18,
      "rights_risk_level": "low",
      "occupancy_risk_level": "low",
      "budget_fit": true,
      "recommendation": "review",
      "item_path": "auctions/items/2024타경103242.json"
    },
    {
      "item_id": "auction-2025-52242-001",
      "case_no": "2025타경52242",
      "status": "watch",
      "priority": 3,
      "region": "수원",
      "sub_region": "장안구",
      "asset_type": "아파트",
      "minimum_price": 297000000,
      "market_price_avg": 290000000,
      "minimum_vs_avg_pct": 2.41,
      "rights_risk_level": "low",
      "occupancy_risk_level": "low",
      "budget_fit": false,
      "recommendation": "watch",
      "item_path": "auctions/items/2025타경52242.json"
    },
    {
      "item_id": "auction-2025-1574-001",
      "case_no": "2025타경1574",
      "status": "pass",
      "priority": 4,
      "region": "수원",
      "sub_region": "영통구",
      "asset_type": "아파트",
      "minimum_price": 359100000,
      "market_price_avg": 596350500,
      "minimum_vs_avg_pct": -39.78,
      "rights_risk_level": "high",
      "occupancy_risk_level": "high",
      "budget_fit": false,
      "recommendation": "pass",
      "item_path": "auctions/items/2025타경1574.json"
    },
    {
      "item_id": "auction-2025-51294-001",
      "case_no": "2025타경51294",
      "status": "pass",
      "priority": 5,
      "region": "수원",
      "sub_region": "팔달구",
      "asset_type": "아파트",
      "minimum_price": 164500000,
      "market_price_avg": 270000000,
      "minimum_vs_avg_pct": -39.07,
      "rights_risk_level": "high",
      "occupancy_risk_level": "high",
      "budget_fit": true,
      "recommendation": "pass",
      "item_path": "auctions/items/2025타경51294.json"
    },
    {
      "item_id": "auction-2025-55649-001",
      "case_no": "2025타경55649",
      "status": "watch",
      "priority": 4,
      "region": "수원",
      "sub_region": "장안구",
      "asset_type": "아파트",
      "minimum_price": 60270000,
      "market_price_avg": 70000000,
      "minimum_vs_avg_pct": -13.9,
      "rights_risk_level": "medium",
      "occupancy_risk_level": "medium",
      "budget_fit": true,
      "recommendation": "watch",
      "item_path": "auctions/items/2025타경55649.json"
    }
  ]
}